daerah_indonesia/__init__.py
daerah_indonesia/daerah_indonesia.cpython-314-x86_64-linux-gnu.so
daerah_indonesia-0.1.0.dist-info/METADATA
daerah_indonesia-0.1.0.dist-info/WHEEL
daerah_indonesia-0.1.0.dist-info/licenses/LICENSE
daerah_indonesia-0.1.0.dist-info/RECORD
