Metadata-Version: 2.4
Name: daerah_indonesia
Version: 0.1.0
Classifier: Programming Language :: Rust
Classifier: Programming Language :: Python
Classifier: License :: OSI Approved :: MIT License
License-File: LICENSE
Summary: Library Python untuk data wilayah Indonesia (Provinsi sampai Kelurahan) + Validasi NIK.
Author-email: Nestero <nestero@mail.com>
Requires-Python: >=3.14
